vertexauth/__init__.py
vertexauth/anthropic.py
vertexauth/claudette.py
vertexauth/core.py
vertexauth-0.2.0.dist-info/METADATA
vertexauth-0.2.0.dist-info/WHEEL
vertexauth-0.2.0.dist-info/RECORD
