Metadata-Version: 2.1
Name: vertexauth
Version: 0.2.0
Summary: Helper for authenticating with VertexAI
Author: Alexis Gallagher
Author-email: alexis@alexisgallagher.com
Requires-Python: >=3.10
Classifier: Programming Language :: Python :: 3
Classifier: Programming Language :: Python :: 3.10
Classifier: Programming Language :: Python :: 3.11
Classifier: Programming Language :: Python :: 3.12
Classifier: Programming Language :: Python :: 3.13
Requires-Dist: anthropic[vertex] (>=0.37.1)
Requires-Dist: claudette (>=0.1.0)
